synth_pdb/__init__.py
synth_pdb/batch_generator.py
synth_pdb/biophysics.py
synth_pdb/chemical_shifts.py
synth_pdb/cofactors.py
synth_pdb/contact.py
synth_pdb/coupling.py
synth_pdb/data.py
synth_pdb/dataset.py
synth_pdb/decoys.py
synth_pdb/distogram.py
synth_pdb/docking.py
synth_pdb/evolution.py
synth_pdb/export.py
synth_pdb/generator.py
synth_pdb/geometry.py
synth_pdb/j_coupling.py
synth_pdb/main.py
synth_pdb/nef_io.py
synth_pdb/nmr.py
synth_pdb/packing.py
synth_pdb/pdb_utils.py
synth_pdb/physics.py
synth_pdb/relaxation.py
synth_pdb/scoring.py
synth_pdb/structure_utils.py
synth_pdb/torsion.py
synth_pdb/validator.py
synth_pdb/viewer.py
synth_pdb/visualization.py
synth_pdb-1.14.0.dist-info/licenses/LICENSE
synth_pdb-1.14.0.dist-info/METADATA
synth_pdb-1.14.0.dist-info/WHEEL
synth_pdb-1.14.0.dist-info/entry_points.txt
synth_pdb-1.14.0.dist-info/top_level.txt
synth_pdb-1.14.0.dist-info/RECORD
