Metadata-Version: 2.4
Name: synth-pdb
Version: 1.14.0
Summary: Generate realistic PDB files with mixed secondary structures for bioinformatics testing, education, and tool development
Author-email: George Elkins <george@example.com>
License: MIT
Project-URL: Homepage, https://github.com/elkins/synth-pdb
Project-URL: Repository, https://github.com/elkins/synth-pdb
Project-URL: Bug Tracker, https://github.com/elkins/synth-pdb/issues
Project-URL: Documentation, https://github.com/elkins/synth-pdb#readme
Project-URL: Changelog, https://github.com/elkins/synth-pdb/releases
Keywords: pdb,protein,structure,bioinformatics,testing,peptide-generation,molecular-modeling,ramachandran,secondary-structure,structural-biology,protein-folding,educational-tool
Classifier: Development Status :: 4 - Beta
Classifier: Intended Audience :: Science/Research
Classifier: Intended Audience :: Education
Classifier: Intended Audience :: Developers
Classifier: Topic :: Scientific/Engineering :: Bio-Informatics
Classifier: Topic :: Scientific/Engineering :: Chemistry
Classifier: Topic :: Education
Classifier: Topic :: Software Development :: Testing
Classifier: Programming Language :: Python :: 3
Classifier: Programming Language :: Python :: 3.8
Classifier: Programming Language :: Python :: 3.9
Classifier: Programming Language :: Python :: 3.10
Classifier: Programming Language :: Python :: 3.11
Classifier: Programming Language :: Python :: 3.12
Classifier: Operating System :: OS Independent
Classifier: Environment :: Console
Requires-Python: >=3.8
License-File: LICENSE
Requires-Dist: numpy<2.0.0,>=1.20.0
Requires-Dist: biotite>=0.35.0
Requires-Dist: openmm>=8.0.0
Requires-Dist: numba>=0.57.0
Provides-Extra: dev
Requires-Dist: pytest>=7.0.0; extra == "dev"
Requires-Dist: pytest-cov>=4.0.0; extra == "dev"
Requires-Dist: black>=23.0.0; extra == "dev"
Requires-Dist: ruff>=0.1.0; extra == "dev"
Requires-Dist: mypy>=1.0.0; extra == "dev"
Requires-Dist: pytest-mock>=3.10.0; extra == "dev"
Dynamic: license-file
